ychatty/__init__.py
ychatty/cli.py
ychatty-0.1.0.dist-info/METADATA
ychatty-0.1.0.dist-info/WHEEL
ychatty-0.1.0.dist-info/entry_points.txt
ychatty-0.1.0.dist-info/licenses/LICENSE
ychatty-0.1.0.dist-info/RECORD
