Metadata-Version: 2.4
Name: ychatty
Version: 0.1.0
Summary: A simple and friendly command-line chat interface with colorful output
Project-URL: Homepage, https://github.com/zokrezyl/chatty
Project-URL: Repository, https://github.com/zokrezyl/chatty.git
Project-URL: Issues, https://github.com/zokrezyl/chatty/issues
Author-email: zokrezyl <zokrezyl@gmail.com>
License-File: LICENSE
Keywords: chat,cli,colorful,interactive,terminal
Classifier: Development Status :: 4 - Beta
Classifier: Intended Audience :: Developers
Classifier: Intended Audience :: End Users/Desktop
Classifier: License :: OSI Approved :: MIT License
Classifier: Operating System :: OS Independent
Classifier: Programming Language :: Python :: 3
Classifier: Programming Language :: Python :: 3.8
Classifier: Programming Language :: Python :: 3.9
Classifier: Programming Language :: Python :: 3.10
Classifier: Programming Language :: Python :: 3.11
Classifier: Programming Language :: Python :: 3.12
Classifier: Topic :: Terminals
Classifier: Topic :: Utilities
Requires-Python: >=3.8
Requires-Dist: click>=8.0.0
Requires-Dist: rich>=13.0.0
